<?xml version="1.0"?>
<uXML language="Ylike" scope="static" var-declaration="no"><block><!--def fun ( n ) --><function name="fun"><automatic-Var><var mutable="yes" name="n" type="Dynamic"/></automatic-Var><block><!--if n == 1 --><operator value="=="><variable name="n"/><constant type="int" value="1"/><block><!--return 1 --><return><constant type="int" value="1"/></return></block><!--else --><block><!--return n * call fun ( n - 1 ) --><return><operator value="*"><variable name="n"/><call><variable name="fun"/><operator value="-"><variable name="n"/><constant type="int" value="1"/></operator></call></operator></return></block></operator></block></function><!--print call fun ( 5 ) --><print><call><variable name="fun"/><constant type="int" value="5"/></call></print></block></uXML>